LICENSE
MANIFEST.in
setup.py
playstvrecovery/__init__.py
playstvrecovery/cli.py
playstvrecovery/playstv.py
playstvrecovery.egg-info/PKG-INFO
playstvrecovery.egg-info/SOURCES.txt
playstvrecovery.egg-info/dependency_links.txt
playstvrecovery.egg-info/entry_points.txt
playstvrecovery.egg-info/requires.txt
playstvrecovery.egg-info/top_level.txt
tests/__init__.py
tests/test_playstv.py