Metadata-Version: 2.1
Name: playstvrecovery
Version: 0.4.2
Summary: A simple tool to recover deleted Plays.tv clips
Author: Nicola Goderis
License-File: LICENSE
